{"k5PikN1meMTNjGImXSYqIA==":"6-958x960.jpg","lrQqUcHLqFenNScYVoNF1A==":"img-20200104-wa0014-1069x1425.jpg","ApxqWvrD2Pveo1fyknEV+Q==":"img-20200104-wa0012-1200x1600.jpg","vofkYcXhfvENFWGLlYwNbg==":"img-20191202-wa0021-1200x1600.jpg","jUf//1DSQtPLZDXwmucHQw==":"img-20191202-wa0041-1200x1600.jpg","pYBpPJnF3q277mZO+YeCHQ==":"img-20191202-wa0036-768x1024.jpg","GmTXpKOAZkzATJjUi6y5cw==":"img-20191202-wa0016-1200x1600.jpg","/C9FUeoGTpCAyzIkCZSsSQ==":"img-20191202-wa0040-1200x1600.jpg","IU3oTq7gtEMblkfyah8V7g==":"img-20191202-wa0043-1200x1600.jpg","eq3Tup2Ct4Yyb1HkxTAVkw==":"img-20191202-wa0029-1200x1600.jpg","60SdQK+R0GCGNVFGps83Jg==":"img-20191202-wa0035-1200x1600.jpg","yb4TJaGyKroLYNbBQQ/MeA==":"img-20191202-wa0024-900x1600.jpg","7vG0agd/P2pLk4C4vsJirA==":"img-20191202-wa0024-900x1600.jpeg","NSgs3sjuf9Ol5d7ibJIjMA==":"img-20191202-wa0042-1200x1600.jpg","JQezUL+Pol9YqbAcEI/abw==":"img-20191202-wa0013-855x1519.jpg","lL0HQhEJqcqqTD6HSx5hUQ==":"img-20191202-wa0013-855x1519.jpeg","XoqyyQjcvDzVkeMd2GFVRA==":"img-20191202-wa0019-1200x1600.jpg","CyqPIg9wpovt+MniTOvx9Q==":"img-20170714-wa0025-810x1080.jpg","7o7IflTauQ+LwLLbrN0+vQ==":"img-20191202-wa0034-1200x1600.jpg","t4UpEOPYns2T3gOR9FVjfA==":"img-20200104-wa0013-900x1600.jpeg","fNPQaHEE4WGHdpKZ4R+Biw==":"img-20200104-wa0013-1-900x1600.jpeg","zGG/3l1PIvI1lQ+ly5p+iw==":"img-20191202-wa0013-1-855x1519.jpeg","TYBJkcKQWzIiaf3OtzwRIw==":"img-20200104-wa0013-2-900x1600.jpeg","CkNlAFYM7dQeS2jgWLWOzw==":"5-953x960.jpg","yPojCUfVb/wzxVspqd4kPA==":"1-466x960.jpeg","fUJ6BDDQxviv03F0hmzbYA==":"1-1-466x960.jpeg","AlRDrm2b5jj6k4VF60lNIg==":"1-2-466x960.jpeg","1+yc9GGPinWGXUwUuL4RNQ==":"img-20180414-wa0000-1200x1600.jpeg","13kkwNsiUqaogCmDftV4pw==":"img-20180414-wa0013-1200x1600.jpeg","x4QtTtWagUv4VG65MPn60Q==":"img-20180414-wa0013-1-1200x1600.jpeg","g6a5WlfjIQZ7WUjOgLRzTw==":"img-20191202-wa0022-1200x1600.jpeg","84J2Ta+NFjNJ7+YFx3CGDQ==":"img-20191202-wa0038-1200x1600.jpeg","ufmIXORkWoH6/d0U9XwE3Q==":"img-20191202-wa0015-1200x1600.jpeg","sIz1W4yVhTsy6NlbOKFiKQ==":"img-20170311-wa0017-960x1280.jpeg","eMoTb1K7yGLsFFm7YeR4dA==":"img-20200104-wa0025-173x128.jpg","JqFy+GM+5HxSfSrnffQdxw==":"img-20200104-wa0025-128x95.jpg","CUGP8iemmAdQHL+sBdvraA==":"img-20200105-wa0001-128x128.jpg"}